OneBotAdapter/Core.py
OneBotAdapter/__init__.py
erispulse_onebotadapter-1.0.0.dist-info/licenses/LICENSE
erispulse_onebotadapter-1.0.0.dist-info/METADATA
erispulse_onebotadapter-1.0.0.dist-info/WHEEL
erispulse_onebotadapter-1.0.0.dist-info/entry_points.txt
erispulse_onebotadapter-1.0.0.dist-info/top_level.txt
erispulse_onebotadapter-1.0.0.dist-info/RECORD
