Metadata-Version: 2.4
Name: ErisPulse-OneBotAdapter
Version: 1.0.0
Summary: ErisPulse的OneBotV11协议适配模块，异步的OneBot触发器
Author-email: wsu2059 <wsu2059@qq.com>
License: MIT License
Project-URL: homepage, https://github.com/ErisPulse/ErisPulse-OneBotAdapter
Requires-Python: >=3.9
License-File: LICENSE
Dynamic: license-file
